{"version": "1", "message": "ERROR: Hidden Testcases server unreachable.", "problem_id": "ads2_m1_a1_1", "user_id": "rishikaharithaMSIT", "score": {"sample": {"0": {"execution_time": 0.3737795352935791, "passed": true}, "1": {"execution_time": 0.35233449935913086, "passed": true}, "2": {"execution_time": 0.3888421058654785, "passed": true}, "3": {"execution_time": 0.3710920810699463, "passed": true}, "4": {"execution_time": 0.41728997230529785, "passed": true}, "5": {"execution_time": 0.34688377380371094, "passed": true}, "6": {"execution_time": 0.3386685848236084, "passed": true}, "7": {"execution_time": 0.3945343494415283, "passed": true}}}, "check_style_score": "0/1"}