{"version": "1", "message": "ERROR: Hidden Testcases server unreachable.", "problem_id": "ads2_m10_a1_1", "user_id": "rishikaharithaMSIT", "score": {"sample": {"0": {"execution_time": 0.5299911499023438, "passed": true}, "1": {"execution_time": 0.519798994064331, "passed": true}, "2": {"execution_time": 0.4597179889678955, "passed": false}, "3": {"execution_time": 0.16214942932128906, "passed": true}, "4": {"execution_time": 0.4803650379180908, "passed": false}, "5": {"execution_time": 0.469937801361084, "passed": false}, "6": {"execution_time": 0.4702301025390625, "passed": false}, "7": {"execution_time": 0.41024041175842285, "passed": false}, "8": {"execution_time": 1.5821003913879395, "passed": false}}}, "check_style_score": "0/1"}