{"version": "1", "message": "ERROR: Hidden Testcases server unreachable.", "problem_id": "ads2_m13_a1_1", "user_id": "rishikaharithaMSIT", "score": {"sample": {"0": {"execution_time": 0.23082208633422852, "passed": true}, "1": {"execution_time": 0.23781132698059082, "passed": true}, "2": {"execution_time": 0.22504377365112305, "passed": true}, "3": {"execution_time": 0.2201244831085205, "passed": true}, "4": {"execution_time": 0.204437255859375, "passed": true}, "5": {"execution_time": 0.25003647804260254, "passed": true}, "6": {"execution_time": 0.24691247940063477, "passed": true}, "7": {"execution_time": 0.21147799491882324, "passed": true}}}, "check_style_score": "1/1"}